LICENSE
README.md
goingnats.py
setup.py
goingnats.egg-info/PKG-INFO
goingnats.egg-info/SOURCES.txt
goingnats.egg-info/dependency_links.txt
goingnats.egg-info/top_level.txt