Metadata-Version: 2.1
Name: goingnats
Version: 2022.3.1
Summary: a Python NATS client
Home-page: http://github.com/3kwa/goingnats
Author: Eugene Van den Bulke
Author-email: eugene.vandenbulke@gmail.com
License: Unlicensed
Platform: UNKNOWN
Classifier: Development Status :: 4 - Beta
Classifier: Intended Audience :: Developers
Classifier: Topic :: Software Development :: Libraries
License-File: LICENSE
